{ "id_specie" : "4020", "common_name" : { "fr" : "Rossignol philomèle" }, "scientific_name" : "Luscinia megarhynchos", "period_start" : "4", "period_end" : "9", "physical_characteristics" : "plumage brun. Ressemble à une grande Fauvette; avec queue brun-roux et le dessous gris crème; gorge blanchâtre; sexes identiques. Les jeunes, à la fin de l'été, sont tachetés de brun et de roussâtre.", "habitat_characteristics" : "forêt buissonneuse", "nesting_characteristics" : "strate herbacée", "wingspan" : "25", "food" : "insectes, araignées", "size" : "16", "weight" : "22", "behavior" : "migrateur au long cours", "comment" : "nicheur et migrateur régulier, peu fréquent", "website" : "www.vogelwarte.ch/fr/oiseaux/les-oiseaux-de-suisse/rossignol-philomele.html", "family_name" : "Turdidae", "class_name" : "Oiseaux (animaux vertébrés)", "reign_name" : "Animaux", "theme_name" : "bird", "owner_name" : "Station ornithologique suisse" }
