{ "id_specie" : "15", "common_name" : { "fr" : "Zygène de la Filipendule" }, "scientific_name" : "filipendulae", "period_start" : "6", "period_end" : "7", "physical_characteristics_adult" : "noir avec des reflets bleu-vert clair et des taches rouges. Ailes postérieures rouges avec une marge noire. Sexes semblables.", "physical_characteristics_child" : "La chenille vert-pâle est tachetée de noir. Elle se nourrit de lotier (Lotus).", "habitat_characteristics" : "prés fleuris jusqu'à 2000 m environ.", "wingspan" : "3.4", "website" : "http://www.photospapillons.com/papillons-de-france-photos.php?num=93", "family_name" : "Zygaenidae", "class_name" : "Insectes (animaux invertébrés)", "reign_name" : "Animaux", "theme_name" : "butterfly", "owner_name" : "Association de la Grande Cariçaie" }
